startle/__init__.py
startle/_console.py
startle/_docstr.py
startle/_help.py
startle/_metavar.py
startle/_parse.py
startle/_register.py
startle/_start.py
startle/_type_utils.py
startle/_value_parser.py
startle/_version.py
startle/arg.py
startle/args.py
startle/cmds.py
startle/error.py
startle/py.typed
startle/_inspect/classes.py
startle/_inspect/dataclasses.py
startle/_inspect/make_args.py
startle/_inspect/names.py
startle/_inspect/parameter.py
startle/_inspect/typeddict.py
startle-0.0.21.dist-info/METADATA
startle-0.0.21.dist-info/WHEEL
startle-0.0.21.dist-info/licenses/LICENSE
startle-0.0.21.dist-info/RECORD
