Metadata-Version: 2.4
Name: startle
Version: 0.0.21
Summary: Instantly start a CLI from functions or classes
Project-URL: Homepage, https://github.com/oir/startle
Author: Ozan Irsoy
License:                                  Apache License
License-File: LICENSE
Keywords: argparse,cli,command line interface
Classifier: Development Status :: 3 - Alpha
Classifier: Intended Audience :: Developers
Classifier: Programming Language :: Python :: 3.10
Classifier: Programming Language :: Python :: 3.11
Classifier: Programming Language :: Python :: 3.12
Classifier: Programming Language :: Python :: 3.13
Classifier: Topic :: Software Development
Requires-Python: >=3.10
Requires-Dist: rich
